verifyforge/__init__.py
verifyforge/client.py
verifyforge/errors.py
verifyforge/types.py
verifyforge-1.0.1.dist-info/licenses/LICENSE
verifyforge-1.0.1.dist-info/METADATA
verifyforge-1.0.1.dist-info/WHEEL
verifyforge-1.0.1.dist-info/top_level.txt
verifyforge-1.0.1.dist-info/RECORD
