Metadata-Version: 2.4
Name: verifyforge
Version: 1.0.1
Summary: Official Python SDK for VerifyForge Email Validation API
Author-email: VerifyForge <contact@verifyforge.com>
License: MIT
Project-URL: Homepage, https://verifyforge.com
Project-URL: Documentation, https://verifyforge.com/api-docs
Project-URL: Repository, https://github.com/VerifyForge/python-sdk
Project-URL: Bug Tracker, https://github.com/VerifyForge/python-sdk/issues
Keywords: email,validation,verification,api,sdk
Classifier: Development Status :: 5 - Production/Stable
Classifier: Intended Audience :: Developers
Classifier: License :: OSI Approved :: MIT License
Classifier: Operating System :: OS Independent
Classifier: Programming Language :: Python :: 3
Classifier: Programming Language :: Python :: 3.8
Classifier: Programming Language :: Python :: 3.9
Classifier: Programming Language :: Python :: 3.10
Classifier: Programming Language :: Python :: 3.11
Classifier: Programming Language :: Python :: 3.12
Classifier: Topic :: Software Development :: Libraries :: Python Modules
Classifier: Topic :: Communications :: Email
Classifier: Topic :: Internet :: WWW/HTTP
Requires-Python: >=3.8
License-File: LICENSE
Requires-Dist: requests>=2.31.0
Provides-Extra: dev
Requires-Dist: pytest>=7.4.0; extra == "dev"
Requires-Dist: pytest-cov>=4.1.0; extra == "dev"
Requires-Dist: black>=23.7.0; extra == "dev"
Requires-Dist: mypy>=1.5.0; extra == "dev"
Requires-Dist: ruff>=0.0.287; extra == "dev"
Dynamic: license-file
